icsmcp/__init__.py
icsmcp/py.typed
icsmcp/server.py
icsmcp-0.1.0.dist-info/METADATA
icsmcp-0.1.0.dist-info/WHEEL
icsmcp-0.1.0.dist-info/entry_points.txt
icsmcp-0.1.0.dist-info/licenses/LICENSE
icsmcp-0.1.0.dist-info/RECORD
