Metadata-Version: 2.4
Name: icsmcp
Version: 0.1.0
Author-email: narumi <toucans-cutouts0f@icloud.com>
License-File: LICENSE
Requires-Python: >=3.12
Requires-Dist: ics>=0.7.2
Requires-Dist: loguru>=0.7.3
Requires-Dist: mcp[cli]>=1.6.0
